CHANGELOG.txt
LICENSE.txt
MANIFEST.in
README.txt
setup.py
anand_calculator.egg-info/PKG-INFO
anand_calculator.egg-info/SOURCES.txt
anand_calculator.egg-info/dependency_links.txt
anand_calculator.egg-info/top_level.txt
calculator/__init__.py
calculator.egg-info/SOURCES.txt
calculator.egg-info/dependency_links.txt
calculator.egg-info/top_level.txt