Metadata-Version: 1.1
Name: anand-calculator
Version: 0.0.1
Summary: A very basic calculator
Home-page: UNKNOWN
Author: Anand Rane
Author-email: arane0017@gmail.com
License: MIT
Keywords: calculator
Platform: UNKNOWN
Classifier: Development Status :: 5 - Production/Stable
Classifier: Intended Audience :: Education
Classifier: Operating System :: Microsoft :: Windows
Classifier: License :: OSI Approved :: MIT License
Classifier: Programming Language :: Python :: 3
